netkiller/__init__.py
netkiller/firewall.py
netkiller_firewall-0.0.1.dist-info/LICENSE
netkiller_firewall-0.0.1.dist-info/METADATA
netkiller_firewall-0.0.1.dist-info/WHEEL
netkiller_firewall-0.0.1.dist-info/top_level.txt
netkiller_firewall-0.0.1.dist-info/RECORD
