Metadata-Version: 2.1
Name: netkiller-firewall
Version: 0.0.1
Summary: Netkiller Python firewall
Home-page: https://github.com/netkiller/firewall
Author: Neo Chen
Author-email: netkiller@msn.com
License: MIT
Platform: UNKNOWN
Classifier: Programming Language :: Python :: 3
Classifier: License :: OSI Approved :: MIT License
Classifier: Operating System :: OS Independent
